setup.py
ghizmo/__init__.py
ghizmo/configs.py
ghizmo/ghizmo.py
ghizmo/main.py
ghizmo.egg-info/PKG-INFO
ghizmo.egg-info/SOURCES.txt
ghizmo.egg-info/dependency_links.txt
ghizmo.egg-info/entry_points.txt
ghizmo.egg-info/requires.txt
ghizmo.egg-info/top_level.txt
ghizmo/commands/__init__.py
ghizmo/commands/authors.py
ghizmo/commands/general.py
ghizmo/commands/lib.py
ghizmo/commands/misc.py
ghizmo/commands/repo.py
ghizmo/commands/team.py
ghizmo/commands/users.py