Metadata-Version: 1.1
Name: ghizmo
Version: 0.1.12
Summary: ghizmo: An extensible command line for GitHub
Home-page: https://github.com/jlevy/ghizmo
Author: Joshua Levy
Author-email: UNKNOWN
License: Apache 2
Platform: UNKNOWN
Classifier: Development Status :: 4 - Beta
Classifier: Environment :: Console
Classifier: Intended Audience :: End Users/Desktop
Classifier: Intended Audience :: System Administrators
Classifier: Intended Audience :: Developers
Classifier: License :: OSI Approved :: Apache Software License
Classifier: Operating System :: MacOS :: MacOS X
Classifier: Operating System :: POSIX
Classifier: Operating System :: Unix
Classifier: Programming Language :: Python :: 2.7
Classifier: Topic :: Utilities
Classifier: Topic :: Software Development
